ngsolve_webgpu/__init__.py
ngsolve_webgpu/_version.py
ngsolve_webgpu/animate.py
ngsolve_webgpu/cf.py
ngsolve_webgpu/clipping.py
ngsolve_webgpu/geometry.py
ngsolve_webgpu/isosurface.py
ngsolve_webgpu/jupyter.py
ngsolve_webgpu/lic.py
ngsolve_webgpu/mesh.py
ngsolve_webgpu/surface_vectors.py
ngsolve_webgpu/shaders/compute.wgsl
ngsolve_webgpu/shaders/elements3d.wgsl
ngsolve_webgpu/shaders/geo_edge.wgsl
ngsolve_webgpu/shaders/geo_face.wgsl
ngsolve_webgpu/shaders/geo_vertex.wgsl
ngsolve_webgpu/shaders/line_integral_convolution.wgsl
ngsolve_webgpu/shaders/mesh.wgsl
ngsolve_webgpu/shaders/numbers.wgsl
ngsolve_webgpu/shaders/shader.wgsl
ngsolve_webgpu/shaders/surface_vectors.wgsl
ngsolve_webgpu/shaders/uniforms.wgsl
ngsolve_webgpu/shaders/clipping/common.wgsl
ngsolve_webgpu/shaders/clipping/compute.wgsl
ngsolve_webgpu/shaders/clipping/render.wgsl
ngsolve_webgpu/shaders/eval/common.wgsl
ngsolve_webgpu/shaders/eval/seg.wgsl
ngsolve_webgpu/shaders/eval/tet.wgsl
ngsolve_webgpu/shaders/eval/trig.wgsl
ngsolve_webgpu/shaders/isosurface/compute.wgsl
ngsolve_webgpu/shaders/isosurface/negative_clipping.wgsl
ngsolve_webgpu/shaders/isosurface/negative_surface.wgsl
ngsolve_webgpu/shaders/isosurface/render.wgsl
ngsolve_webgpu-0.1.2.dist-info/licenses/LICENSE
ngsolve_webgpu-0.1.2.dist-info/METADATA
ngsolve_webgpu-0.1.2.dist-info/WHEEL
ngsolve_webgpu-0.1.2.dist-info/top_level.txt
ngsolve_webgpu-0.1.2.dist-info/RECORD
