Metadata-Version: 2.4
Name: ngsolve_webgpu
Version: 0.1.2
Summary: WebGPU/Pyodide based rendering tools for Netgen/NGSolve
Author-email: Matthias Hochsteger <mhochsteger@cerbsim.com>, Christopher Lackner <clackner@cerbsim.com>
License-Expression: LGPL-2.1-or-later
Keywords: WebGPU,compute shaders,graphics,Python,NGSolve,FEM,Netgen
Classifier: Programming Language :: Python :: 3
Classifier: Operating System :: OS Independent
Requires-Python: >=3.8
License-File: LICENSE
Dynamic: license-file
